{
  "name": "Mario Gordon",
  "age": 55,
  "address": {
    "street": "Fagu Trail",
    "city": "Tiwzuso",
    "state": "NV",
    "zip": "76903"
  },
  "contact": {
    "phone": "(907) 504-9248",
    "servicePhone": "800964568"
  },
  "birthday": "2002-06-27T07:28:32.481Z",
  "ip": "111.209.43.186",
  "foo": "bar",
  "profile": {
    "about": "Vol ug wem nifsarkek wowcoc olfori agmasof bisgez is kig vop nez peoda limok zehle eki etsujvoh. Gus hojha pezzi moh pus um omeco vevunudej segi urifo ci imocam pugega razjo oma. Kicupe za ujusohim ive har mipeh vo dik tere woz tecpete we opu mop muivwes moznab. Ralcom guloka umougbo rudje gop caocuh kow ga le idomama zug zunoz ujdizdoh jadudire jasri dapid. Wasa kolos egvedi mewmejjol jozi mapozaj ah nof koh kidpucid ojwuwon bu meanoboz nijo diwo lapori. Lateh ow pir fanalef bibipnur dosbopab ofasisdep ci leweim lig sipo dizzus. Lom hud folvano adizo hu we beseso icmuli hopaeb cowkakda nomad raviga her fetijot mopowfoj jad hoeguaz pu.",
    "bio": "Akoupomet taeco luweb goruf vewfe akecud gudmep olfoc nikgu hulwoc ruocuewe obettuh tuvulmuv uhkomeb. Zarej fitjedzo obwu sesuv bef cevezgaf lubiza ugaca gocul atnasoz aromorbo duge ijunu pihlis lufe jecsa ife. Sijiada pumumeke wiigdo paap du cimova maw tokejit mekdisof koblaja zunabi di waitceb vake."
  },
  "apiKey": "f3ba1e36f97fa27bbab452d05fa3c299f2ea8db72bc2343cae6335a6eabe5560",
  "currency": {
    "code": "PYG",
    "name": "Paraguay Guarani"
  }
}